dbt_graph_builder/__init__.py
dbt_graph_builder/builder.py
dbt_graph_builder/gateway.py
dbt_graph_builder/graph.py
dbt_graph_builder/node_type.py
dbt_graph_builder/utils.py
dbt_graph_builder/workflow.py
dbt_graph_builder-0.7.0.dist-info/LICENSE
dbt_graph_builder-0.7.0.dist-info/METADATA
dbt_graph_builder-0.7.0.dist-info/WHEEL
dbt_graph_builder-0.7.0.dist-info/top_level.txt
dbt_graph_builder-0.7.0.dist-info/RECORD
