Metadata-Version: 2.1
Name: dbt-graph-builder
Version: 0.7.0
Summary: DBT Graph Builder
Author-email: Piotr Pękala <piotr.pekala@getindata.com>, Andrzej Swatowski <andrzej.swatowski@getindata.com>, Piotr Tutak <piotr.tutak@getindata.com>
License: MIT License
Classifier: Development Status :: 3 - Alpha
Classifier: Intended Audience :: Developers
Classifier: License :: OSI Approved :: MIT License
Classifier: Programming Language :: Python :: 3 :: Only
Classifier: Programming Language :: Python :: 3.8
Classifier: Programming Language :: Python :: 3.9
Classifier: Programming Language :: Python :: 3.10
Classifier: Programming Language :: Python :: 3.11
Requires-Python: >=3.8
License-File: LICENSE
Requires-Dist: networkx <3,>=2.6
